Metadata-Version: 2.1
Name: django-superuser-required
Version: 2020.7.1
Summary: Django SuperuserRequiredMixin - request.user.is_superuser==True required
Home-page: https://github.com/andrewp-as-is/django-superuser-required.py
License: Unlicense
Keywords: django superuser
Platform: UNKNOWN
Classifier: Framework :: Django
Classifier: License :: Public Domain
Classifier: Operating System :: OS Independent
Classifier: Programming Language :: Python :: 3
